{
  "images": [
    "mongo",
    "phpmyadmin/phpmyadmin",
    "mysql"
  ],
  "containers": [
    {
      "containerID": "682a2cb10dee",
      "image": "phpmyadmin/phpmyadmin",
      "command": "/run.sh phpmyadmin",
      "created": "25 hours ago",
      "status": "Exited (0) 22 minutes ago",
      "status_server": false,
      "port": "",
      "name": "phpmyadmin"
    },
    {
      "containerID": "190e72c73e1a",
      "image": "mysql",
      "command": "docker-entrypoint.s…",
      "created": "25 hours ago",
      "status": "Exited (0) 20 seconds ago",
      "status_server": false,
      "port": "",
      "name": "mysql_db_server"
    }
  ]
}